{
  "$schema": "https://developer.microsoft.com/json-schemas/fabric/item/report/definition/visualContainer/2.5.0/schema.json",
  "name": "f25673d5ac374e6ff6ff",
  "position": {
    "x": 26.935873738091853,
    "y": 71.343665576567616,
    "z": 1,
    "height": 159.43125266600313,
    "width": 327.59846438219824,
    "tabOrder": 1
  },
  "visual": {
    "visualType": "cardVisual",
    "query": {
      "queryState": {
        "Data": {
          "projections": [
            {
              "field": {
                "Aggregation": {
                  "Expression": {
                    "Column": {
                      "Expression": {
                        "SourceRef": {
                          "Entity": "fact_sale"
                        }
                      },
                      "Property": "Profit"
                    }
                  },
                  "Function": 0
                }
              },
              "queryRef": "Sum(fact_sale.Profit)",
              "nativeQueryRef": "Sum of Profit"
            }
          ]
        }
      },
      "sortDefinition": {
        "sort": [
          {
            "field": {
              "Aggregation": {
                "Expression": {
                  "Column": {
                    "Expression": {
                      "SourceRef": {
                        "Entity": "fact_sale"
                      }
                    },
                    "Property": "Profit"
                  }
                },
                "Function": 0
              }
            },
            "direction": "Descending"
          }
        ],
        "isDefaultSort": true
      }
    },
    "objects": {
      "padding": [
        {
          "properties": {
            "paddingUniform": {
              "expr": {
                "Literal": {
                  "Value": "12L"
                }
              }
            }
          },
          "selector": {
            "id": "default"
          }
        }
      ],
      "layout": [
        {
          "properties": {
            "alignment": {
              "expr": {
                "Literal": {
                  "Value": "'middle'"
                }
              }
            }
          }
        }
      ],
      "value": [
        {
          "properties": {
            "horizontalAlignment": {
              "expr": {
                "Literal": {
                  "Value": "'center'"
                }
              }
            }
          },
          "selector": {
            "id": "default"
          }
        }
      ]
    },
    "drillFilterOtherVisuals": true
  },
  "filterConfig": {
    "filters": [
      {
        "name": "b61acb78641dd4ab2b10",
        "field": {
          "Aggregation": {
            "Expression": {
              "Column": {
                "Expression": {
                  "SourceRef": {
                    "Entity": "fact_sale"
                  }
                },
                "Property": "Profit"
              }
            },
            "Function": 0
          }
        },
        "type": "Advanced"
      }
    ]
  }
}